<?xml version="1.0" encoding="UTF-8"?>
<flowconnector:FlowConnectorDefinition xmi:version="2.0" xmlns:xmi="http://www.omg.org/XMI" xmlns:xsi="http://www.w3.org/2001/XMLSchema-instance" xmlns:flowconnector="http://www.founderfix.com/flowconnector" id="CreateSubpProcessData" name="创建子流程数据" note="启动子流程后需要插入一个默认的数据" categoryId="a5dedc5f-a22d-4429-a161-705eb26b6938" icon="CreateSubpProcessData.jpg">
  <input id="table" type="java.lang.String" mandatory="是" defaultValue=""/>
  <input id="param" type="java.util.HashMap" mandatory="是" defaultValue=""/>
  <page id="page1" name="创建子流程参数" note="创建子流程参数">
    <widget xsi:type="flowconnector:Text" id="Widget_0" name="表名" inputId="table">
      <widgetExpression expressionValue=""/>
    </widget>
    <widget xsi:type="flowconnector:Text" id="Widget_1" name="参数" inputId="param">
      <widgetExpression expressionValue=""/>
    </widget>
  </page>
  <definitionImpl className="CreateSubpProcessData" packageName="com.founder.fix.fixflow.expand.flowconnector.CreateSubpProcessData"/>
</flowconnector:FlowConnectorDefinition>
